[{"_id":"61a667c0d56a2600d5a9460c","name":"Batch Demo Videos","type":"BATCH_SCHEDULE_VIDEO","typeId":"61a2301c8cfae00011598dba","displayOrder":1,"notes":1,"exercises":0,"videos":1,"slug":"batch-demo-videos-702259"},{"_id":"61a667dc5259a90018a63e9a","name":"Lecture Planner II (Only PDF)","type":"BATCH_SCHEDULE_VIDEO","typeId":"61a2301c8cfae00011598dba","displayOrder":2,"notes":3,"exercises":0,"videos":0,"slug":"lecture-planner-ii--only-pdf--742413"},{"_id":"61a667f4c9f6f50018d876b3","name":"Test Planner II (Only PDF)","type":"BATCH_SCHEDULE_VIDEO","typeId":"61a2301c8cfae00011598dba","displayOrder":3,"notes":3,"exercises":0,"videos":0,"slug":"test-planner-ii--only-pdf--022242"},{"_id":"61a6699a5e38d2009e7c8218","name":"Class Schedule II (Only PDF)","type":"BATCH_SCHEDULE_VIDEO","typeId":"61a2301c8cfae00011598dba","displayOrder":4,"notes":3,"exercises":0,"videos":0,"slug":"class-schedule-ii--only-pdf--900035"},{"_id":"61c028390c01fa0018d38aaa","name":"Test","type":"BATCH_SCHEDULE_VIDEO","typeId":"61a2301c8cfae00011598dba","displayOrder":5,"notes":24,"exercises":0,"videos":24,"slug":"test-283157"},{"_id":"61ac99eac5afb200182246d6","name":"Telegram Group for Information || (Only PDF)","type":"BATCH_SCHEDULE_VIDEO","typeId":"61a2301c8cfae00011598dba","displayOrder":6,"notes":1,"exercises":0,"videos":0,"slug":"telegram-group-for-information-||--only-pdf--047323"},{"_id":"61e5764c34908d017f0ed0ad","name":"Live Session","type":"BATCH_SCHEDULE_VIDEO","typeId":"61a2301c8cfae00011598dba","displayOrder":8,"notes":0,"exercises":0,"videos":1,"slug":"live-session-093365"},{"_id":"61ea9501ec27360018e35574","name":"Student Queries In DPP","type":"BATCH_SCHEDULE_VIDEO","typeId":"61a2301c8cfae00011598dba","displayOrder":9,"notes":0,"exercises":0,"videos":3,"slug":"student-queries-in-dpp-041199"},{"_id":"61b749c8b12ae30011efe5d4","name":"Test Schedule and Syllabus","type":"BATCH_SCHEDULE_VIDEO","typeId":"61a2301c8cfae00011598dba","displayOrder":10,"notes":1,"exercises":0,"videos":0,"slug":"test-schedule-and-syllabus-771344"},{"_id":"625d0bffd9dfbf001132da64","name":"Handbook Material","type":"BATCH_SCHEDULE_VIDEO","typeId":"61a2301c8cfae00011598dba","displayOrder":13,"notes":1,"exercises":0,"videos":0,"slug":"handbook-material-954727"},{"_id":"61adc5e753f8f0020454d5ed","name":"Ch-01: Basics Mathematics","type":"BATCH_SCHEDULE_VIDEO","typeId":"61a2301c8cfae00011598dba","displayOrder":16,"notes":6,"exercises":0,"videos":4,"slug":"ch-01--basics-mathematics-394420"},{"_id":"61af8cef73605c00117993d7","name":"Ch-02: Quadratic Equation","type":"BATCH_SCHEDULE_VIDEO","typeId":"61a2301c8cfae00011598dba","displayOrder":17,"notes":9,"exercises":0,"videos":6,"slug":"ch-02--quadratic-equation-157596"},{"_id":"61b3678980e1f50012664f03","name":"Ch-03: Sequence And Series","type":"BATCH_SCHEDULE_VIDEO","typeId":"61a2301c8cfae00011598dba","displayOrder":20,"notes":9,"exercises":0,"videos":6,"slug":"ch-03--sequence-and-series-329932"},{"_id":"61b8ce11fc95020018c66f40","name":"Ch-04: Permutations & Combinations","type":"BATCH_SCHEDULE_VIDEO","typeId":"61a2301c8cfae00011598dba","displayOrder":24,"notes":9,"exercises":0,"videos":6,"slug":"ch-04--permutations-and-combinations-602338"},{"_id":"61bcb2be7fe8840018494b0d","name":"Ch-05: Binomial Theorem","type":"BATCH_SCHEDULE_VIDEO","typeId":"61a2301c8cfae00011598dba","displayOrder":26,"notes":6,"exercises":0,"videos":4,"slug":"ch-05--binomial-theorem-614479"},{"_id":"61c0e6a6451f5e0011971653","name":"Ch-06: Complex Number","type":"BATCH_SCHEDULE_VIDEO","typeId":"61a2301c8cfae00011598dba","displayOrder":29,"notes":9,"exercises":0,"videos":6,"slug":"ch-06--complex-number-675963"},{"_id":"61c49c87ceea4c014adcb060","name":"Ch-07 : Matrices and Determinant","type":"BATCH_SCHEDULE_VIDEO","typeId":"61a2301c8cfae00011598dba","displayOrder":33,"notes":9,"exercises":0,"videos":6,"slug":"ch-07---matrices-and-determinant-051686"},{"_id":"61cb262727099001af763d80","name":"Ch-08 : Trigonometry","type":"BATCH_SCHEDULE_VIDEO","typeId":"61a2301c8cfae00011598dba","displayOrder":37,"notes":12,"exercises":0,"videos":8,"slug":"ch-08---trigonometry-892053"},{"_id":"61d3164fa450890018d66eff","name":"Ch-09 : Straight Lines","type":"BATCH_SCHEDULE_VIDEO","typeId":"61a2301c8cfae00011598dba","displayOrder":39,"notes":9,"exercises":0,"videos":6,"slug":"ch-09---straight-lines-381095"},{"_id":"61d7035c3fe0dc0018af8be4","name":"Ch-10 : Conic Section","type":"BATCH_SCHEDULE_VIDEO","typeId":"61a2301c8cfae00011598dba","displayOrder":44,"notes":18,"exercises":6,"videos":12,"slug":"ch-10---conic-section-382860"},{"_id":"61e04f5bf83343004c43a2fe","name":"Ch-11 : Sets","type":"BATCH_SCHEDULE_VIDEO","typeId":"61a2301c8cfae00011598dba","displayOrder":49,"notes":3,"exercises":1,"videos":2,"slug":"ch-11---sets-748395"},{"_id":"61e1ce49138cda0018605400","name":"Ch-12 : Inverse Trigonometry Function","type":"BATCH_SCHEDULE_VIDEO","typeId":"61a2301c8cfae00011598dba","displayOrder":50,"notes":6,"exercises":2,"videos":4,"slug":"ch-12---inverse-trigonometry-function-765879"},{"_id":"61e5810052810e0011458b0a","name":"Ch-13 : Relations & Functions","type":"BATCH_SCHEDULE_VIDEO","typeId":"61a2301c8cfae00011598dba","displayOrder":52,"notes":13,"exercises":1,"videos":9,"slug":"ch-13---relations-and-functions-187999"},{"_id":"61eafb813ebf750018d7d2cc","name":"Ch-14 : Limits and Derivatives","type":"BATCH_SCHEDULE_VIDEO","typeId":"61a2301c8cfae00011598dba","displayOrder":58,"notes":6,"exercises":0,"videos":4,"slug":"ch-14---limits-and-derivatives-819468"},{"_id":"61f1929b80c5f8001160433b","name":"Ch-15 : Continuity And Differentiability","type":"BATCH_SCHEDULE_VIDEO","typeId":"61a2301c8cfae00011598dba","displayOrder":60,"notes":6,"exercises":2,"videos":4,"slug":"ch-15---continuity-and-differentiability-998446"},{"_id":"61f2eaaf7ea20600186661bb","name":"Ch-16 : Applications of Derivatives","type":"BATCH_SCHEDULE_VIDEO","typeId":"61a2301c8cfae00011598dba","displayOrder":63,"notes":13,"exercises":4,"videos":9,"slug":"ch-16---applications-of-derivatives-871832"},{"_id":"61faa740888ace00189ed92e","name":"Ch-17 : Definite and Indefinite Integrals","type":"BATCH_SCHEDULE_VIDEO","typeId":"61a2301c8cfae00011598dba","displayOrder":64,"notes":19,"exercises":6,"videos":13,"slug":"ch-17---definite-and-indefinite-integrals-549776"},{"_id":"62054f69441f0900118c8107","name":"Ch-18 : Area Under the Curve","type":"BATCH_SCHEDULE_VIDEO","typeId":"61a2301c8cfae00011598dba","displayOrder":71,"notes":6,"exercises":2,"videos":4,"slug":"ch-18---area-under-the-curve-973834"},{"_id":"62096749525c3e00187ffaab","name":"Ch-19 : Differential Equation","type":"BATCH_SCHEDULE_VIDEO","typeId":"61a2301c8cfae00011598dba","displayOrder":74,"notes":6,"exercises":2,"videos":4,"slug":"ch-19---differential-equation-587543"},{"_id":"620bf05e3ab8cb0018f1c0a2","name":"Ch-20 : Vector Algebra","type":"BATCH_SCHEDULE_VIDEO","typeId":"61a2301c8cfae00011598dba","displayOrder":77,"notes":7,"exercises":2,"videos":5,"slug":"ch-20---vector-algebra-552385"},{"_id":"620e972887e72c0011f278e5","name":"Ch-21 : 3-D Geometry","type":"BATCH_SCHEDULE_VIDEO","typeId":"61a2301c8cfae00011598dba","displayOrder":78,"notes":7,"exercises":2,"videos":5,"slug":"ch-21---3-d-geometry-073441"},{"_id":"6213cffd9f1a530018978cee","name":"Ch-22 : Probability","type":"BATCH_SCHEDULE_VIDEO","typeId":"61a2301c8cfae00011598dba","displayOrder":82,"notes":9,"exercises":3,"videos":6,"slug":"ch-22---probability-410328"},{"_id":"6217c5d0f837ca0011ed3187","name":"Ch-23 : Statistics","type":"BATCH_SCHEDULE_VIDEO","typeId":"61a2301c8cfae00011598dba","displayOrder":85,"notes":3,"exercises":1,"videos":2,"slug":"ch-23---statistics-069199"},{"_id":"6219287070e0f50018320e23","name":"Ch-24 : Mathematical Reasoning","type":"BATCH_SCHEDULE_VIDEO","typeId":"61a2301c8cfae00011598dba","displayOrder":86,"notes":3,"exercises":1,"videos":2,"slug":"ch-24---mathematical-reasoning-290116"},{"_id":"621bbfdd460baa022796b515","name":"Extra MIP Lectures","type":"BATCH_SCHEDULE_VIDEO","typeId":"61a2301c8cfae00011598dba","displayOrder":88,"notes":21,"exercises":7,"videos":14,"slug":"extra-mip-lectures-797923"},{"_id":"6231918668804e00185a0053","name":"PYQs Revision","type":"BATCH_SCHEDULE_VIDEO","typeId":"61a2301c8cfae00011598dba","displayOrder":99,"notes":56,"exercises":18,"videos":38,"slug":"pyqs-revision-138595"},{"_id":"62c53679d7d9970018ccd010","name":"Advanced Revision","type":"BATCH_SCHEDULE_VIDEO","typeId":"61a2301c8cfae00011598dba","displayOrder":102,"notes":17,"exercises":6,"videos":11,"slug":"advanced-revision-884835"}]