[{"_id":"botany-556849study-module-||--pdf-only--122291","name":"Study Module || (PDF Only)","type":"BATCH_SCHEDULE_VIDEO","typeId":"6311e6d6f8c2d4001842f517","displayOrder":9,"notes":3,"exercises":0,"videos":0,"slug":"study-module-||--pdf-only--122291"},{"_id":"botany-556849ch-01---cell-cycle-and-cell-division-542769","name":"Ch 01 : Cell Cycle and Cell Division","type":"BATCH_SCHEDULE_VIDEO","typeId":"6311e6d6f8c2d4001842f517","displayOrder":13,"notes":15,"exercises":2,"videos":6,"slug":"ch-01---cell-cycle-and-cell-division-542769"},{"_id":"botany-556849ch-02---cell---the-unit-of-life-651217","name":"Ch 02 : Cell - The Unit of Life","type":"BATCH_SCHEDULE_VIDEO","typeId":"6311e6d6f8c2d4001842f517","displayOrder":17,"notes":15,"exercises":5,"videos":10,"slug":"ch-02---cell---the-unit-of-life-651217"},{"_id":"botany-556849ch-03---biological-classification-828019","name":"Ch 03 : Biological Classification","type":"BATCH_SCHEDULE_VIDEO","typeId":"6311e6d6f8c2d4001842f517","displayOrder":29,"notes":10,"exercises":3,"videos":5,"slug":"ch-03---biological-classification-828019"}]