{"videos":[{"_id":"63ced55171dbb6001801b8e8","restrictedSchedule":false,"restrictedTime":0,"urlType":"penpencilvdo","tags":[{"_id":"63cc45c23bb04c0018daf422","name":"Ch-07 : Plant growth and development"}],"isFree":false,"isChatEnabled":false,"isDoubtEnabled":true,"isCommentDisabled":false,"isPathshala":false,"isDPPVideos":false,"status":"PENDING","topic":"Plant growth and development-02 : Physiological Effects of Plant Growth Regulators || Photoperiodism","date":"2023-01-24T18:29:59.000Z","startTime":"2023-01-24T09:00:59.000Z","endTime":"2023-01-24T09:00:59.000Z","timeline":[],"url":"https:\/\/d1d34p8vz63oiq.cloudfront.net\/f7a90226-44a4-47b5-ac31-0dc7829586c8\/master.mpd","videoDetails":{"_id":"63c6a155f8b6f70018c1fa30","id":"63c6a155f8b6f70018c1fa30","name":"Plant growth and development-02: Physiological Effects of Plant Growth Regulators || Photoperiodism","image":"https:\/\/d2bps9p1kiy4ka.cloudfront.net\/5eb393ee95fab7468a79d189\/b4f48ecb-829d-4a9b-90a6-44dbd33835eb.png","videoUrl":"https:\/\/d1d34p8vz63oiq.cloudfront.net\/f7a90226-44a4-47b5-ac31-0dc7829586c8\/master.mpd","duration":"01:12:31","status":"Ready","types":["DASH","HLS"],"createdAt":"2023-01-17T13:23:33.716Z"},"dRoomId":"63a7fdfc252d6a0018015d60","isBatchDoubtEnabled":true},{"_id":"63cd4fef9929b3001845cd80","restrictedSchedule":false,"restrictedTime":0,"urlType":"penpencilvdo","tags":[{"_id":"63cc45c23bb04c0018daf422","name":"Ch-07 : Plant growth and development"}],"isFree":false,"isChatEnabled":false,"isDoubtEnabled":true,"isCommentDisabled":false,"isPathshala":false,"isDPPVideos":false,"status":"PENDING","topic":"Plant growth and development-01 : Growth || Growth Rates","date":"2023-01-23T18:29:59.000Z","startTime":"2023-01-23T09:00:59.000Z","endTime":"2023-01-23T09:00:59.000Z","timeline":[],"url":"https:\/\/d1d34p8vz63oiq.cloudfront.net\/0658981d-8b38-4a7b-84ec-8f8e185fa985\/master.mpd","videoDetails":{"_id":"63c67a25e6a2c70018f7db0d","id":"63c67a25e6a2c70018f7db0d","name":"Plant growth and development-01 : Growth || Growth Rates","image":"https:\/\/d2bps9p1kiy4ka.cloudfront.net\/5eb393ee95fab7468a79d189\/c5edbbdb-57a8-4668-9928-1d57d0d85fbb.png","videoUrl":"https:\/\/d1d34p8vz63oiq.cloudfront.net\/0658981d-8b38-4a7b-84ec-8f8e185fa985\/master.mpd","duration":"01:20:41","status":"Ready","types":["DASH","HLS"],"createdAt":"2023-01-17T10:36:21.263Z"},"dRoomId":"63a7fdfc252d6a0018015d60","isBatchDoubtEnabled":true}],"notes":[{"_id":"63ced55171dbb6001801b8e8","isFree":false,"status":"PENDING","date":"2023-01-24T18:29:59.000Z","startTime":"2023-01-24T09:00:59.000Z","isDPPNotes":false,"homeworkIds":[{"_id":"63cee3af66879400188b77c4","actions":["Open","Download","Print"],"topic":"Plant growth and development-02 : Classnotes II NEET Ultimate CC 2023","note":"Classnotes","attachmentIds":[{"_id":"63cee3ada8bfbe0018226d63","name":"Plant growth and development-02 Classnotes.pdf","baseUrl":"https:\/\/d2bps9p1kiy4ka.cloudfront.net\/","key":"5eb393ee95fab7468a79d189\/e16c9641-79ac-41b2-87b8-d97c0caad713.pdf"}],"batchSubjectId":"639ca78248c7b60018aa9682","solutionVideoType":"none"}],"dRoomId":"63a7fdfc252d6a0018015d60","isBatchDoubtEnabled":true},{"_id":"63cd4fef9929b3001845cd80","isFree":false,"status":"PENDING","date":"2023-01-23T18:29:59.000Z","startTime":"2023-01-23T09:00:59.000Z","isDPPNotes":false,"homeworkIds":[{"_id":"63cd5473f177bd001899ca76","actions":["Open","Download","Print"],"topic":"Plant growth and development-01 : Classnotes II NEET Ultimate CC 2023","note":"Classnotes","attachmentIds":[{"_id":"63cd546a29ca180017ef357e","name":"Plant growth and development-01 Classnotes.pdf","baseUrl":"https:\/\/d2bps9p1kiy4ka.cloudfront.net\/","key":"5eb393ee95fab7468a79d189\/9a3d8e34-d7d9-47ad-8a34-74e3b8f2130b.pdf"}],"batchSubjectId":"639ca78248c7b60018aa9682","solutionVideoType":"none"}],"dRoomId":"63a7fdfc252d6a0018015d60","isBatchDoubtEnabled":true}],"DppNotes":[{"_id":"63cee5d966879400188b8e8e","isFree":false,"status":"PENDING","date":"2023-01-24T18:29:59.000Z","startTime":"2023-01-24T09:00:59.000Z","isDPPNotes":true,"homeworkIds":[{"_id":"63cee3d2d9d0cf001810e2ef","actions":["Open","Download","Print"],"topic":"Plant growth and development : DPP-02 II NEET Ultimate CC 2023","note":"DPP","attachmentIds":[{"_id":"63cee3d0ad14f100190a0a58","name":"Plant growth and development DPP-02.pdf","baseUrl":"https:\/\/d2bps9p1kiy4ka.cloudfront.net\/","key":"5eb393ee95fab7468a79d189\/1e48279b-bd27-4b30-aacc-c0083a97435f.pdf"}],"batchSubjectId":"639ca78248c7b60018aa9682","solutionVideoType":"none"}],"dRoomId":"63a7fdfc252d6a0018015d60","isBatchDoubtEnabled":true},{"_id":"63cd809443c4000018246360","isFree":false,"status":"PENDING","date":"2023-01-23T18:29:59.000Z","startTime":"2023-01-23T09:00:59.000Z","isDPPNotes":true,"homeworkIds":[{"_id":"63cd54b6f177bd001899ca8d","actions":["Open","Download","Print"],"topic":"Plant growth and development : DPP-01 II NEET Ultimate CC 2023","note":"DPP","attachmentIds":[{"_id":"63cd54b40875ac00187c1a0b","name":"Plant growth and development DPP-01.pdf","baseUrl":"https:\/\/d2bps9p1kiy4ka.cloudfront.net\/","key":"5eb393ee95fab7468a79d189\/406fbbad-5535-4f5d-a1dc-a41dbaa505d0.pdf"}],"batchSubjectId":"639ca78248c7b60018aa9682","solutionVideoType":"none"}],"dRoomId":"63a7fdfc252d6a0018015d60","isBatchDoubtEnabled":true}],"DppVideos":[],"exercises":[{"_id":"63cee5d966879400188b8e8e","isFree":false,"status":"PENDING","date":"2023-01-24T18:29:59.000Z","startTime":"2023-01-24T09:00:59.000Z","exerciseIds":[{"type":"Exercise","availableFor":[],"status":"Active","title":"Plant growth and Development : DPP-02 (MCQ Quiz)","content":[{"_id":"63cf0b54e64c0b0018d44660","exerciseId":"63cf0b53fb91e400189693ad","timeline":[]}],"slug":"plant-growth-and-development---dpp-02--mcq-quiz--454997"}],"dRoomId":"63a7fdfc252d6a0018015d60","isBatchDoubtEnabled":true},{"_id":"63cd809443c4000018246360","isFree":false,"status":"PENDING","date":"2023-01-23T18:29:59.000Z","startTime":"2023-01-23T09:00:59.000Z","exerciseIds":[{"type":"Exercise","availableFor":[],"status":"Active","title":"Plant growth and Development : DPP-01 (MCQ Quiz)","content":[{"_id":"63cd7fa21f505f0018bfe727","exerciseId":"63cd7fa2e59ca10018491f9d","timeline":[]}],"slug":"plant-growth-and-development---dpp-01--mcq-quiz--245967"}],"dRoomId":"63a7fdfc252d6a0018015d60","isBatchDoubtEnabled":true}]}