{"videos":[{"_id":"64005d6cdc41c20019f1ae63","restrictedSchedule":false,"restrictedTime":0,"urlType":"penpencilvdo","tags":[{"_id":"63fc60eb96d02d00184d6c86","name":"Consumer Behaviour"}],"isFree":false,"isChatEnabled":false,"isDoubtEnabled":true,"isCommentDisabled":false,"isPathshala":false,"isDPPVideos":false,"status":"PENDING","topic":"Consumer Behaviour 04 : Indifference Curve || Marginal rate of substitution","date":"2023-03-02T18:29:59.000Z","startTime":"2023-03-02T09:45:59.000Z","endTime":"2023-03-02T09:45:59.000Z","timeline":[],"url":"https:\/\/d1d34p8vz63oiq.cloudfront.net\/31c52492-a110-48ad-b33b-03821606dc22\/master.mpd","videoDetails":{"_id":"64005f1115fcbf001867e658","id":"64005f1115fcbf001867e658","name":"Consumer Behavior 04 : Indifference Curve || Marginal rate of substitution (Kanchan Mam) Sampurna Fast-Track","image":"https:\/\/d2bps9p1kiy4ka.cloudfront.net\/5eb393ee95fab7468a79d189\/28dbdf4b-106d-40f9-814b-3be87966d139.jpeg","videoUrl":"https:\/\/d1d34p8vz63oiq.cloudfront.net\/31c52492-a110-48ad-b33b-03821606dc22\/master.mpd","duration":"01:09:23","status":"Ready","types":["DASH","HLS"],"createdAt":"2023-03-02T08:32:17.762Z"},"dRoomId":"63eb5ffb128d7be1d2b939fa","isBatchDoubtEnabled":true},{"_id":"63ff0544fc8cfe007ddab5cf","restrictedSchedule":false,"restrictedTime":0,"urlType":"penpencilvdo","tags":[{"_id":"63fc60eb96d02d00184d6c86","name":"Consumer Behaviour"}],"isFree":false,"isChatEnabled":false,"isDoubtEnabled":true,"isCommentDisabled":false,"isPathshala":false,"isDPPVideos":false,"status":"PENDING","topic":"Consumer Behaviour 03 : Consumer Equilibrium In case of Single & Two commodity || Consumer Surplus","date":"2023-03-01T18:29:59.000Z","startTime":"2023-03-01T09:45:59.000Z","endTime":"2023-03-01T09:45:59.000Z","timeline":[],"url":"https:\/\/d1d34p8vz63oiq.cloudfront.net\/fe5f51df-fc6a-4a4f-84f5-0af2477c1228\/master.mpd","videoDetails":{"_id":"63ff0367a1e0c3005ae97825","id":"63ff0367a1e0c3005ae97825","name":"Consumer Behaviour 03 : Consumer Equilibrium In case of Single & Two commodity || Consumer Surplus  (Kanchan Mam) Sampurna Fast-Track","image":"https:\/\/d2bps9p1kiy4ka.cloudfront.net\/5eb393ee95fab7468a79d189\/fe25c674-eb5c-4b0a-978a-0365137ad782.png","videoUrl":"https:\/\/d1d34p8vz63oiq.cloudfront.net\/fe5f51df-fc6a-4a4f-84f5-0af2477c1228\/master.mpd","duration":"01:09:28","status":"Ready","types":["DASH","HLS"],"createdAt":"2023-03-01T07:48:55.120Z"},"dRoomId":"63eb5ffb128d7be1d2b939fa","isBatchDoubtEnabled":true},{"_id":"63fdb57e36faa50018da82d1","restrictedSchedule":false,"restrictedTime":0,"urlType":"penpencilvdo","tags":[{"_id":"63fc60eb96d02d00184d6c86","name":"Consumer Behaviour"}],"isFree":false,"isChatEnabled":false,"isDoubtEnabled":true,"isCommentDisabled":false,"isPathshala":false,"isDPPVideos":false,"status":"PENDING","topic":"Consumer Behaviour 02 : Diminishing Marginal Utility","date":"2023-02-28T18:29:59.000Z","startTime":"2023-02-28T09:45:59.000Z","endTime":"2023-02-28T09:45:59.000Z","timeline":[],"url":"https:\/\/d1d34p8vz63oiq.cloudfront.net\/b2894728-1688-4fc3-a289-12f7dd930d75\/master.mpd","videoDetails":{"_id":"63fdb47a71200e0019d40988","id":"63fdb47a71200e0019d40988","name":"Consumer Behaviour 02 : Diminishing Marginal Utility  (Kanchan Mam) Sampurna Fast-Track","image":"https:\/\/d2bps9p1kiy4ka.cloudfront.net\/5eb393ee95fab7468a79d189\/cde8f88c-6382-4a06-b097-50be2e35213c.png","videoUrl":"https:\/\/d1d34p8vz63oiq.cloudfront.net\/b2894728-1688-4fc3-a289-12f7dd930d75\/master.mpd","duration":"00:56:04","status":"Ready","types":["DASH","HLS"],"createdAt":"2023-02-28T07:59:54.504Z"},"dRoomId":"63eb5ffb128d7be1d2b939fa","isBatchDoubtEnabled":true},{"_id":"63fc612296d02d00184d6cb3","restrictedSchedule":false,"restrictedTime":0,"urlType":"penpencilvdo","tags":[{"_id":"63fc60eb96d02d00184d6c86","name":"Consumer Behaviour"}],"isFree":false,"isChatEnabled":false,"isDoubtEnabled":true,"isCommentDisabled":false,"isPathshala":false,"isDPPVideos":false,"status":"PENDING","topic":"Consumer Behaviour 01 : Meaning and utility","date":"2023-02-27T18:29:59.000Z","startTime":"2023-02-27T09:45:59.000Z","endTime":"2023-02-27T09:45:59.000Z","timeline":[],"url":"https:\/\/d1d34p8vz63oiq.cloudfront.net\/f8eac274-769e-4cad-aa42-eca3ecc7d61e\/master.mpd","videoDetails":{"_id":"63fc64374605f00018fa6399","id":"63fc64374605f00018fa6399","name":"Consumer Behaviour 01 : Meaning and utility  (Kanchan Mam) Sampurna Fast-Track","image":"https:\/\/d2bps9p1kiy4ka.cloudfront.net\/5eb393ee95fab7468a79d189\/38262125-77c1-401d-b714-b7f42acaddae.png","videoUrl":"https:\/\/d1d34p8vz63oiq.cloudfront.net\/f8eac274-769e-4cad-aa42-eca3ecc7d61e\/master.mpd","duration":"01:02:08","status":"Ready","types":["DASH","HLS"],"createdAt":"2023-02-27T08:05:11.860Z"},"dRoomId":"63eb5ffb128d7be1d2b939fa","isBatchDoubtEnabled":true}],"notes":[{"_id":"64005d6cdc41c20019f1ae63","isFree":false,"status":"PENDING","date":"2023-03-02T18:29:59.000Z","startTime":"2023-03-02T09:45:59.000Z","isDPPNotes":false,"homeworkIds":[{"_id":"64005dabc05d840018e25691","actions":["Open","Download","Print"],"topic":"Consumer Behaviour 04 : Class Notes ( Sampurna Fastrack)","note":"Class Notes","attachmentIds":[{"_id":"64005daadf120a0018c347c6","name":"Consumer Behavior Lec-4 (Kanchan Mam) Sampurna Fast-Track......pdf","baseUrl":"https:\/\/d2bps9p1kiy4ka.cloudfront.net\/","key":"5eb393ee95fab7468a79d189\/8bedf80b-2833-4dff-a2ab-e2e7baf87bf4.pdf"}],"batchSubjectId":"63b594845998c500187494f7","solutionVideoType":"none"}],"dRoomId":"63eb5ffb128d7be1d2b939fa","isBatchDoubtEnabled":true},{"_id":"63ff0544fc8cfe007ddab5cf","isFree":false,"status":"PENDING","date":"2023-03-01T18:29:59.000Z","startTime":"2023-03-01T09:45:59.000Z","isDPPNotes":false,"homeworkIds":[{"_id":"63ff06c4b821e400181fdb8d","actions":["Open","Download","Print"],"topic":"Consumer Behaviour 03 : Class Notes ( Sampurna Fastrack)","note":"Class Notes","attachmentIds":[{"_id":"63ff06c402b79000c0603ecd","name":"Consumer Behavior Lec-3 (Kanchan Mam) Sampurna Fast-Track.pdf","baseUrl":"https:\/\/d2bps9p1kiy4ka.cloudfront.net\/","key":"5eb393ee95fab7468a79d189\/ee046452-94e5-4707-9791-667525ebf900.pdf"}],"batchSubjectId":"63b594845998c500187494f7","solutionVideoType":"none"}],"dRoomId":"63eb5ffb128d7be1d2b939fa","isBatchDoubtEnabled":true},{"_id":"63fdb57e36faa50018da82d1","isFree":false,"status":"PENDING","date":"2023-02-28T18:29:59.000Z","startTime":"2023-02-28T09:45:59.000Z","isDPPNotes":false,"homeworkIds":[{"_id":"63fdbac7fe19bb00183a380d","actions":["Open","Download","Print"],"topic":"Consumer Behaviour 02 : Class Notes ( Sampurna Fastrack)","note":"Class Notes","attachmentIds":[{"_id":"63fdbac62e0ad60018243ab6","name":"Consumer Behavior Lec-2 (Kanchan Mam) Sampurna Fast-Track_.pdf","baseUrl":"https:\/\/d2bps9p1kiy4ka.cloudfront.net\/","key":"5eb393ee95fab7468a79d189\/7290a157-4036-444f-b23c-b084ca0a1575.pdf"}],"batchSubjectId":"63b594845998c500187494f7","solutionVideoType":"none"}],"dRoomId":"63eb5ffb128d7be1d2b939fa","isBatchDoubtEnabled":true},{"_id":"63fc612296d02d00184d6cb3","isFree":false,"status":"PENDING","date":"2023-02-27T18:29:59.000Z","startTime":"2023-02-27T09:45:59.000Z","isDPPNotes":false,"homeworkIds":[{"_id":"63fc61615a432d00189eae39","actions":["Open","Download","Print"],"topic":"Consumer Behaviour  01 : Class Notes ( Sampurna Fastrack)","note":"Class Notes","attachmentIds":[{"_id":"63fc616053cc5a0018359345","name":"Consumer Behavior Lec-1 (Kanchan Mam) Sampurna Fast-Track (1).pdf","baseUrl":"https:\/\/d2bps9p1kiy4ka.cloudfront.net\/","key":"5eb393ee95fab7468a79d189\/6ac9433b-f2fb-4627-99c0-82dc18a5bd77.pdf"}],"batchSubjectId":"63b594845998c500187494f7","solutionVideoType":"none"}],"dRoomId":"63eb5ffb128d7be1d2b939fa","isBatchDoubtEnabled":true}],"DppNotes":[{"_id":"64005e05a237b70018f54dcb","isFree":false,"status":"PENDING","date":"2023-03-02T18:29:59.000Z","startTime":"2023-03-02T09:45:59.000Z","isDPPNotes":true,"homeworkIds":[{"_id":"64005ddda237b70018f54d93","actions":["Open","Download","Print"],"topic":"Consumer Behaviour : DPP 04 || Sampurna Fastrack","note":"DPP","attachmentIds":[{"_id":"64005ddc2d079f001835f309","name":"DPP-04_Theory of Consumer Behaviour_Economics_Sampurna Fastrack_Kanchana Madam_Rajesh (2) (1).pdf","baseUrl":"https:\/\/d2bps9p1kiy4ka.cloudfront.net\/","key":"5eb393ee95fab7468a79d189\/c670db87-c8df-4540-989b-464e6995a9c8.pdf"}],"batchSubjectId":"63b594845998c500187494f7","solutionVideoType":"none"}],"dRoomId":"63eb5ffb128d7be1d2b939fa","isBatchDoubtEnabled":true},{"_id":"63ff070b052e05005161434a","isFree":false,"status":"PENDING","date":"2023-03-01T18:29:59.000Z","startTime":"2023-03-01T09:45:59.000Z","isDPPNotes":true,"homeworkIds":[{"_id":"63ff06ea20c07900ab619f07","actions":["Open","Download","Print"],"topic":"Consumer Behaviour : DPP 03 || Sampurna Fastrack","note":"DPP","attachmentIds":[{"_id":"63ff06ea6727dd004f7c0fe3","name":"DPP-03_Theory of Consumer Behaviour_Economics_Sampurna Fastrack_Kanchana Madam_Rajesh (1).pdf","baseUrl":"https:\/\/d2bps9p1kiy4ka.cloudfront.net\/","key":"5eb393ee95fab7468a79d189\/2ebe811d-d2b9-481f-8758-78fd7890da54.pdf"}],"batchSubjectId":"63b594845998c500187494f7","solutionVideoType":"none"}],"dRoomId":"63eb5ffb128d7be1d2b939fa","isBatchDoubtEnabled":true},{"_id":"63fdbb54fe19bb00183a38a9","isFree":false,"status":"PENDING","date":"2023-02-28T18:29:59.000Z","startTime":"2023-02-28T09:45:59.000Z","isDPPNotes":true,"homeworkIds":[{"_id":"63fdbaf2479760001830bf94","actions":["Open","Download","Print"],"topic":"Consumer Behaviour : DPP 02 || Sampurna Fastrack","note":"DPP","attachmentIds":[{"_id":"63fdbaf10d1fe300188a1104","name":"DPP-02_Theory of Consumer Behaviour_Economics_Sampurna Fastrack_Kanchana Madam_Rajesh (1).pdf","baseUrl":"https:\/\/d2bps9p1kiy4ka.cloudfront.net\/","key":"5eb393ee95fab7468a79d189\/64815e09-6f51-4265-b834-de0ae4e6a5f0.pdf"}],"batchSubjectId":"63b594845998c500187494f7","solutionVideoType":"none"}],"dRoomId":"63eb5ffb128d7be1d2b939fa","isBatchDoubtEnabled":true},{"_id":"63fc6267af1cd100183cd2cb","isFree":false,"status":"PENDING","date":"2023-02-27T18:29:59.000Z","startTime":"2023-02-27T09:45:59.000Z","isDPPNotes":true,"homeworkIds":[{"_id":"63fc61f18a73fc001895b134","actions":["Open","Download","Print"],"topic":"Consumer Behaviour  : DPP 01 || Sampurna Fastrack","note":"DPP","attachmentIds":[{"_id":"63fc7c8eaf1cd100183ce377","name":"Consumer Behaviour  _ DPP 01 __ Sampurna Fastrack (1).pdf","baseUrl":"https:\/\/d2bps9p1kiy4ka.cloudfront.net\/","key":"5eb393ee95fab7468a79d189\/a7f293ad-3db5-4a5c-883a-b269e2ef8076.pdf"}],"batchSubjectId":"63b594845998c500187494f7","solutionVideoType":"none"}],"dRoomId":"63eb5ffb128d7be1d2b939fa","isBatchDoubtEnabled":true}],"DppVideos":[{"_id":"6401a27c35c0b200189f7f58","restrictedSchedule":false,"restrictedTime":0,"urlType":"penpencilvdo","tags":[{"_id":"63fc60eb96d02d00184d6c86","name":"Consumer Behaviour"}],"isFree":false,"isChatEnabled":false,"isDoubtEnabled":false,"isCommentDisabled":false,"isPathshala":false,"isDPPVideos":true,"status":"PENDING","topic":"Consumer Behaviour Solution to DPP 04","date":"2023-03-03T18:29:59.000Z","startTime":"2023-03-03T08:30:00.000Z","endTime":"2023-03-03T08:30:00.000Z","url":"https:\/\/d1d34p8vz63oiq.cloudfront.net\/0602d0d5-a6c2-41de-bc05-fdb46b943224\/master.mpd","timeline":[],"videoDetails":{"_id":"6401844035c0b200189ec91d","id":"6401844035c0b200189ec91d","name":"Consumer Behaviour DPP 04","image":"https:\/\/d2bps9p1kiy4ka.cloudfront.net\/5eb393ee95fab7468a79d189\/96789eb0-1402-474c-8260-90da171dd075.png","videoUrl":"https:\/\/d1d34p8vz63oiq.cloudfront.net\/0602d0d5-a6c2-41de-bc05-fdb46b943224\/master.mpd","duration":"00:35:26","status":"Ready","types":["DASH","HLS"],"createdAt":"2023-03-03T05:23:12.144Z"},"dRoomId":"63eb5ffb128d7be1d2b939fa","isBatchDoubtEnabled":true},{"_id":"64003a69c307b700184f9454","restrictedSchedule":false,"restrictedTime":0,"urlType":"penpencilvdo","tags":[{"_id":"63fc60eb96d02d00184d6c86","name":"Consumer Behaviour"}],"isFree":false,"isChatEnabled":false,"isDoubtEnabled":false,"isCommentDisabled":false,"isPathshala":false,"isDPPVideos":true,"status":"PENDING","topic":"Consumer Behaviour Solution to DPP 03","date":"2023-03-02T18:29:59.000Z","startTime":"2023-03-02T08:30:00.000Z","endTime":"2023-03-02T08:30:00.000Z","url":"https:\/\/d1d34p8vz63oiq.cloudfront.net\/d5c469f3-3cb1-4f54-9007-4901225795c3\/master.mpd","timeline":[],"videoDetails":{"_id":"64002f29199cc9001823c217","id":"64002f29199cc9001823c217","name":"Consumer Behaviour  DPP 03","image":"https:\/\/d2bps9p1kiy4ka.cloudfront.net\/5eb393ee95fab7468a79d189\/0351aeeb-ba04-4fb8-9bc5-717cabe6ec9c.png","videoUrl":"https:\/\/d1d34p8vz63oiq.cloudfront.net\/d5c469f3-3cb1-4f54-9007-4901225795c3\/master.mpd","duration":"00:36:14","status":"Ready","types":["DASH","HLS"],"createdAt":"2023-03-02T05:07:53.879Z"},"dRoomId":"63eb5ffb128d7be1d2b939fa","isBatchDoubtEnabled":true},{"_id":"63fee40820c07900ab616dd3","restrictedSchedule":false,"restrictedTime":0,"urlType":"penpencilvdo","tags":[{"_id":"63fc60eb96d02d00184d6c86","name":"Consumer Behaviour"}],"isFree":false,"isChatEnabled":false,"isDoubtEnabled":false,"isCommentDisabled":false,"isPathshala":false,"isDPPVideos":true,"status":"PENDING","topic":"Consumer Behaviour Solution to DPP 02","date":"2023-03-01T18:29:59.000Z","startTime":"2023-03-01T08:30:00.000Z","endTime":"2023-03-01T08:30:00.000Z","url":"https:\/\/d1d34p8vz63oiq.cloudfront.net\/1d6c8559-6c93-4a1f-b98c-6c2f59cb1111\/master.mpd","timeline":[],"videoDetails":{"_id":"63fedcdf76aae9004b5790ed","id":"63fedcdf76aae9004b5790ed","name":"Consumer Behaviour DPP 02","image":"https:\/\/d2bps9p1kiy4ka.cloudfront.net\/5eb393ee95fab7468a79d189\/0ff469de-f130-4a82-89f5-aa18e6912c71.png","videoUrl":"https:\/\/d1d34p8vz63oiq.cloudfront.net\/1d6c8559-6c93-4a1f-b98c-6c2f59cb1111\/master.mpd","duration":"00:09:15","status":"Ready","types":["DASH","HLS"],"createdAt":"2023-03-01T05:04:31.272Z"},"dRoomId":"63eb5ffb128d7be1d2b939fa","isBatchDoubtEnabled":true},{"_id":"63fd9f3f23c0d5001856d0f7","restrictedSchedule":false,"restrictedTime":0,"urlType":"penpencilvdo","tags":[{"_id":"63fc60eb96d02d00184d6c86","name":"Consumer Behaviour"}],"isFree":false,"isChatEnabled":false,"isDoubtEnabled":false,"isCommentDisabled":false,"isPathshala":false,"isDPPVideos":true,"status":"PENDING","topic":"Consumer Behaviour Solution to DPP  01","date":"2023-02-28T18:29:59.000Z","startTime":"2023-02-28T08:30:00.000Z","endTime":"2023-02-28T08:30:00.000Z","url":"https:\/\/d1d34p8vz63oiq.cloudfront.net\/d1ce15c4-40ec-4639-b977-2cf6e55b9fc0\/master.mpd","timeline":[],"videoDetails":{"_id":"63fd96170436710018016add","id":"63fd96170436710018016add","name":"Consumer Behaviour DPP 01","image":"https:\/\/d2bps9p1kiy4ka.cloudfront.net\/5eb393ee95fab7468a79d189\/3e9cc3e7-7382-4665-ab03-ee3851daed8c.png","videoUrl":"https:\/\/d1d34p8vz63oiq.cloudfront.net\/d1ce15c4-40ec-4639-b977-2cf6e55b9fc0\/master.mpd","duration":"00:33:21","status":"Ready","types":["DASH","HLS"],"createdAt":"2023-02-28T05:50:15.135Z"},"dRoomId":"63eb5ffb128d7be1d2b939fa","isBatchDoubtEnabled":true}],"exercises":[]}