{"videos":[{"_id":"64002b2e94cc4b001820eabf","restrictedSchedule":false,"restrictedTime":0,"urlType":"penpencilvdo","tags":[{"_id":"63f99456d9d5db0018b298a1","name":"Time Value Of Money"}],"isFree":false,"isChatEnabled":false,"isDoubtEnabled":true,"isCommentDisabled":false,"isPathshala":false,"isDPPVideos":false,"status":"PENDING","topic":"Time Value Of Money 05 : Previous Year Questions","date":"2023-03-02T18:29:59.000Z","startTime":"2023-03-02T08:00:59.000Z","endTime":"2023-03-02T08:00:59.000Z","timeline":[],"url":"https:\/\/d1d34p8vz63oiq.cloudfront.net\/a61d1155-5d3f-4d2b-902e-6b7479e11d34\/master.mpd","videoDetails":{"_id":"640028ca5bdb280018fbe0cf","id":"640028ca5bdb280018fbe0cf","name":"Time Value Of Money 05 : Previous Year Questions ||  ( Rahul Sir ) Sampurna Fastrack","image":"https:\/\/d2bps9p1kiy4ka.cloudfront.net\/5eb393ee95fab7468a79d189\/a2dedf95-3935-4fca-8c8d-94acd6d020d1.png","videoUrl":"https:\/\/d1d34p8vz63oiq.cloudfront.net\/a61d1155-5d3f-4d2b-902e-6b7479e11d34\/master.mpd","duration":"01:22:30","status":"Ready","types":["DASH","HLS"],"createdAt":"2023-03-02T04:40:42.155Z"},"dRoomId":"63eb5ffb128d7be1d2b939fa","isBatchDoubtEnabled":true},{"_id":"63fedd19b821e400181f39d9","restrictedSchedule":false,"restrictedTime":0,"urlType":"penpencilvdo","tags":[{"_id":"63f99456d9d5db0018b298a1","name":"Time Value Of Money"}],"isFree":false,"isChatEnabled":false,"isDoubtEnabled":true,"isCommentDisabled":false,"isPathshala":false,"isDPPVideos":false,"status":"PENDING","topic":"Time Value Of Money 04 : Applications of Annuity","date":"2023-03-01T18:29:59.000Z","startTime":"2023-03-01T08:00:59.000Z","endTime":"2023-03-01T08:00:59.000Z","timeline":[],"url":"https:\/\/d1d34p8vz63oiq.cloudfront.net\/154cf45c-0fb8-4551-afb8-a2a3430034d2\/master.mpd","videoDetails":{"_id":"63fed553e5ba670018a129e2","id":"63fed553e5ba670018a129e2","name":"Time Value Of Money 04 : Applications of Annuity ||  ( Rahul Sir ) Sampurna Fastrack","image":"https:\/\/d2bps9p1kiy4ka.cloudfront.net\/5eb393ee95fab7468a79d189\/d34e96d5-46ee-4fe3-9596-04a7a6882f20.png","videoUrl":"https:\/\/d1d34p8vz63oiq.cloudfront.net\/154cf45c-0fb8-4551-afb8-a2a3430034d2\/master.mpd","duration":"01:26:05","status":"Ready","types":["DASH","HLS"],"createdAt":"2023-03-01T04:32:19.240Z"},"dRoomId":"63eb5ffb128d7be1d2b939fa","isBatchDoubtEnabled":true},{"_id":"63fd9216e7faaa0018355b59","restrictedSchedule":false,"restrictedTime":0,"urlType":"penpencilvdo","tags":[{"_id":"63f99456d9d5db0018b298a1","name":"Time Value Of Money"}],"isFree":false,"isChatEnabled":false,"isDoubtEnabled":true,"isCommentDisabled":false,"isPathshala":false,"isDPPVideos":false,"status":"PENDING","topic":"Time Value Of Money 03 : Future Value || Present Value of Annuity","date":"2023-02-28T18:29:59.000Z","startTime":"2023-02-28T08:00:59.000Z","endTime":"2023-02-28T08:00:59.000Z","timeline":[],"url":"https:\/\/d1d34p8vz63oiq.cloudfront.net\/f089ca10-f069-4186-8a78-89f34aa70321\/master.mpd","videoDetails":{"_id":"63fd97a8a6389300183025b1","id":"63fd97a8a6389300183025b1","name":"Time Value Of Money 03 : Future Value || Present Value of Annuity  ( Rahul Sir ) Sampurna Fastrack","image":"https:\/\/d2bps9p1kiy4ka.cloudfront.net\/5eb393ee95fab7468a79d189\/a1a075d6-4fa0-410b-8f23-1325f25085a0.png","videoUrl":"https:\/\/d1d34p8vz63oiq.cloudfront.net\/f089ca10-f069-4186-8a78-89f34aa70321\/master.mpd","duration":"01:48:56","status":"Ready","types":["DASH","HLS"],"createdAt":"2023-02-28T05:56:56.208Z"},"dRoomId":"63eb5ffb128d7be1d2b939fa","isBatchDoubtEnabled":true},{"_id":"63fc34935376bb01699a1427","restrictedSchedule":false,"restrictedTime":0,"urlType":"penpencilvdo","tags":[{"_id":"63f99456d9d5db0018b298a1","name":"Time Value Of Money"}],"isFree":false,"isChatEnabled":false,"isDoubtEnabled":true,"isCommentDisabled":false,"isPathshala":false,"isDPPVideos":false,"status":"PENDING","topic":"Time Value Of Money 02 : Conversion Period || Effective Rate Of Interest || PYQs","date":"2023-02-27T18:29:59.000Z","startTime":"2023-02-27T08:00:59.000Z","endTime":"2023-02-27T08:00:59.000Z","timeline":[],"url":"https:\/\/d1d34p8vz63oiq.cloudfront.net\/b395afb3-2f9c-4eb9-9527-7fffb99b4a74\/master.mpd","videoDetails":{"_id":"63fc24edc840f2006609c671","id":"63fc24edc840f2006609c671","name":"Time Value Of Money 02 : Conversion Period || Effective Rate Of Interest || PYQs   ( Rahul Bhutani ) Sampurna Fastrack","image":"https:\/\/d2bps9p1kiy4ka.cloudfront.net\/5eb393ee95fab7468a79d189\/55bdacec-2a34-477a-b3cb-0bb7e5df8588.png","videoUrl":"https:\/\/d1d34p8vz63oiq.cloudfront.net\/b395afb3-2f9c-4eb9-9527-7fffb99b4a74\/master.mpd","duration":"01:20:39","status":"Ready","types":["DASH","HLS"],"createdAt":"2023-02-27T03:35:09.166Z"},"dRoomId":"63eb5ffb128d7be1d2b939fa","isBatchDoubtEnabled":true},{"_id":"63f994884891e900186c41b6","restrictedSchedule":false,"restrictedTime":0,"urlType":"penpencilvdo","tags":[{"_id":"63f99456d9d5db0018b298a1","name":"Time Value Of Money"}],"isFree":false,"isChatEnabled":false,"isDoubtEnabled":true,"isCommentDisabled":false,"isPathshala":false,"isDPPVideos":false,"status":"PENDING","topic":"Time Value Of Money 01 : Simple Interest || Compound Interest","date":"2023-02-25T18:29:59.000Z","startTime":"2023-02-25T08:00:59.000Z","endTime":"2023-02-25T08:00:59.000Z","timeline":[],"url":"https:\/\/d1d34p8vz63oiq.cloudfront.net\/9b6dbf98-7ef3-475e-9de9-32b4770a4464\/master.mpd","videoDetails":{"_id":"63f886a97f9e63001809c131","id":"63f886a97f9e63001809c131","name":"Time Value Of Money 01 : Simple Interest || Compound Interest ||   ( Rahul Bhutani ) Sampurna Fastrack","image":"https:\/\/d2bps9p1kiy4ka.cloudfront.net\/5eb393ee95fab7468a79d189\/18760167-79fd-4e32-83c4-f6d4064257c4.png","videoUrl":"https:\/\/d1d34p8vz63oiq.cloudfront.net\/9b6dbf98-7ef3-475e-9de9-32b4770a4464\/master.mpd","duration":"01:35:11","status":"Ready","types":["DASH","HLS"],"createdAt":"2023-02-24T09:43:05.169Z"},"dRoomId":"63eb5ffb128d7be1d2b939fa","isBatchDoubtEnabled":true}],"notes":[{"_id":"64002b2e94cc4b001820eabf","isFree":false,"status":"PENDING","date":"2023-03-02T18:29:59.000Z","startTime":"2023-03-02T08:00:59.000Z","isDPPNotes":false,"homeworkIds":[{"_id":"64002c75199cc9001823c169","actions":["Open","Download","Print"],"topic":"Time Value Of Money 05 : Class Notes ( Sampurna Fastrack)","note":"Class Notes","attachmentIds":[{"_id":"64002c745bdb280018fbf42b","name":"20230225165136339 (1).pdf","baseUrl":"https:\/\/d2bps9p1kiy4ka.cloudfront.net\/","key":"5eb393ee95fab7468a79d189\/eb4d7ffa-3029-454d-ae18-99a13d3467ce.pdf"}],"batchSubjectId":"63b594845998c500187494f5","solutionVideoType":"none"}],"dRoomId":"63eb5ffb128d7be1d2b939fa","isBatchDoubtEnabled":true},{"_id":"63fedd19b821e400181f39d9","isFree":false,"status":"PENDING","date":"2023-03-01T18:29:59.000Z","startTime":"2023-03-01T08:00:59.000Z","isDPPNotes":false,"homeworkIds":[{"_id":"63fee0a6a47dc700182b955a","actions":["Open","Download","Print"],"topic":"Time Value Of Money 04 : Class Notes ( Sampurna Fastrack)","note":"Class Notes","attachmentIds":[{"_id":"63fee0a46727dd004f7a8576","name":"04_Time Value of Money_Commerce sampurna Fasttrack__Rahul sir_Vikram Singhfinal (1).pdf","baseUrl":"https:\/\/d2bps9p1kiy4ka.cloudfront.net\/","key":"5eb393ee95fab7468a79d189\/e5d3ea31-4554-4211-b863-4dcc13f1e097.pdf"}],"batchSubjectId":"63b594845998c500187494f5","solutionVideoType":"none"}],"dRoomId":"63eb5ffb128d7be1d2b939fa","isBatchDoubtEnabled":true},{"_id":"63fd9216e7faaa0018355b59","isFree":false,"status":"PENDING","date":"2023-02-28T18:29:59.000Z","startTime":"2023-02-28T08:00:59.000Z","isDPPNotes":false,"homeworkIds":[{"_id":"63fd930fd99c5a00195522f6","actions":["Open","Download","Print"],"topic":"Time Value Of Money 03 : Class Notes ( Sampurna Fastrack)","note":"Class Notes","attachmentIds":[{"_id":"63fd930e04c9c0001864921a","name":",,,,,,03_Time Value of Money_Commerce sampurna Fasttrack__Rahul sir_Vikram Singh (1) (1).pdf","baseUrl":"https:\/\/d2bps9p1kiy4ka.cloudfront.net\/","key":"5eb393ee95fab7468a79d189\/54628664-90cd-49b8-89ac-c24b8d67921d.pdf"}],"batchSubjectId":"63b594845998c500187494f5","solutionVideoType":"none"}],"dRoomId":"63eb5ffb128d7be1d2b939fa","isBatchDoubtEnabled":true},{"_id":"63fc34935376bb01699a1427","isFree":false,"status":"PENDING","date":"2023-02-27T18:29:59.000Z","startTime":"2023-02-27T08:00:59.000Z","isDPPNotes":false,"homeworkIds":[{"_id":"63fc359bc840f200660a365e","actions":["Open","Download","Print"],"topic":"Time Value Of Money 02 : Class Notes ( Sampurna Fastrack)","note":"Class Notes","attachmentIds":[{"_id":"63fc359b46bb3f00189c3e45","name":"Time Value of Money 02_Commerce sampurna Fasttrack__Rahul sir_Vikram Singh.pdf","baseUrl":"https:\/\/d2bps9p1kiy4ka.cloudfront.net\/","key":"5eb393ee95fab7468a79d189\/33b20f4f-090d-4258-ba12-faf5684b23b3.pdf"}],"batchSubjectId":"63b594845998c500187494f5","solutionVideoType":"none"}],"dRoomId":"63eb5ffb128d7be1d2b939fa","isBatchDoubtEnabled":true},{"_id":"63f994884891e900186c41b6","isFree":false,"status":"PENDING","date":"2023-02-25T18:29:59.000Z","startTime":"2023-02-25T08:00:59.000Z","isDPPNotes":false,"homeworkIds":[{"_id":"63f99cf7dce35d0018992f0f","actions":["Open","Download","Print"],"topic":"Time Value Of Money 01 : Class Notes ( Sampurna Fastrack)","note":"Class Notes","attachmentIds":[{"_id":"63f99cf64891e900186c48e0","name":"time value of money lec - 01.pdf","baseUrl":"https:\/\/d2bps9p1kiy4ka.cloudfront.net\/","key":"5eb393ee95fab7468a79d189\/a0f2f6ea-ffa7-42cd-9ae0-91acf598c6da.pdf"}],"batchSubjectId":"63b594845998c500187494f5","solutionVideoType":"none"}],"dRoomId":"63eb5ffb128d7be1d2b939fa","isBatchDoubtEnabled":true}],"DppNotes":[{"_id":"64002ccd797c45001860ea16","isFree":false,"status":"PENDING","date":"2023-03-02T18:29:59.000Z","startTime":"2023-03-02T08:00:59.000Z","isDPPNotes":true,"homeworkIds":[{"_id":"64002caac307b700184f3207","actions":["Open","Download","Print"],"topic":"Time Value Of Money : DPP 05 || Sampurna Fastrack","note":"DPP","attachmentIds":[{"_id":"64002ca96dbeca00186d07c2","name":"FASTRACK-DPP _05_ Bussiness Maths _Time Value of Money _Vandana  -     (1).pdf","baseUrl":"https:\/\/d2bps9p1kiy4ka.cloudfront.net\/","key":"5eb393ee95fab7468a79d189\/abecd62f-7d4b-4c2d-b882-f9f8b6dbf561.pdf"}],"batchSubjectId":"63b594845998c500187494f5","solutionVideoType":"none"}],"dRoomId":"63eb5ffb128d7be1d2b939fa","isBatchDoubtEnabled":true},{"_id":"63fee107401c400018ab0fa1","isFree":false,"status":"PENDING","date":"2023-03-01T18:29:59.000Z","startTime":"2023-03-01T08:00:59.000Z","isDPPNotes":true,"homeworkIds":[{"_id":"63fee0e16727dd004f7a858c","actions":["Open","Download","Print"],"topic":"Time Value Of Money : DPP 04 || Sampurna Fastrack","note":"DPP","attachmentIds":[{"_id":"63fee0e05091a90062b45b12","name":"Fastrack_DPP _04_ Bussiness Maths _Time Value of Money _Vandana_final.pdf","baseUrl":"https:\/\/d2bps9p1kiy4ka.cloudfront.net\/","key":"5eb393ee95fab7468a79d189\/edce3814-2350-4732-a259-e735660f868e.pdf"}],"batchSubjectId":"63b594845998c500187494f5","solutionVideoType":"none"}],"dRoomId":"63eb5ffb128d7be1d2b939fa","isBatchDoubtEnabled":true},{"_id":"63fd939fa5ba7400180fade5","isFree":false,"status":"PENDING","date":"2023-02-28T18:29:59.000Z","startTime":"2023-02-28T08:00:59.000Z","isDPPNotes":true,"homeworkIds":[{"_id":"63fd933904c9c0001864921d","actions":["Open","Download","Print"],"topic":"Time Value Of Money : DPP 03 || Sampurna Fastrack","note":"DPP","attachmentIds":[{"_id":"63fd93372a02c100182d597f","name":"FASTRACK_DPP _03_ Bussiness Maths _Time Value of Money _Vandana  -  .pdf","baseUrl":"https:\/\/d2bps9p1kiy4ka.cloudfront.net\/","key":"5eb393ee95fab7468a79d189\/c7e39ffb-658c-4986-a98d-7be14b0a1cfa.pdf"}],"batchSubjectId":"63b594845998c500187494f5","solutionVideoType":"none"}],"dRoomId":"63eb5ffb128d7be1d2b939fa","isBatchDoubtEnabled":true},{"_id":"63fc361a7e63ee0018894df2","isFree":false,"status":"PENDING","date":"2023-02-27T18:29:59.000Z","startTime":"2023-02-27T08:00:59.000Z","isDPPNotes":true,"homeworkIds":[{"_id":"63fc35c47e63ee0018894de6","actions":["Open","Download","Print"],"topic":"Time Value Of Money : DPP 02 || Sampurna Fastrack","note":"DPP","attachmentIds":[{"_id":"63fc35c2f6580800188a0498","name":"Final_DPP _02_ Bussiness Maths _Time Value of Money _Vandana  -    .pdf","baseUrl":"https:\/\/d2bps9p1kiy4ka.cloudfront.net\/","key":"5eb393ee95fab7468a79d189\/17d659ca-2960-4699-b30a-cc73b5515203.pdf"}],"batchSubjectId":"63b594845998c500187494f5","solutionVideoType":"none"}],"dRoomId":"63eb5ffb128d7be1d2b939fa","isBatchDoubtEnabled":true},{"_id":"63f99e0d9adabb00184706d3","isFree":false,"status":"PENDING","date":"2023-02-25T18:29:59.000Z","startTime":"2023-02-25T08:00:59.000Z","isDPPNotes":true,"homeworkIds":[{"_id":"63f99d7f39e06f0018c25fdd","actions":["Open","Download","Print"],"topic":"Time Value Of Money : DPP 01 || Sampurna Fastrack","note":"DPP","attachmentIds":[{"_id":"63f99d7e59e8cd0018e10de8","name":"DPP _01_ Bussiness Maths _Time Value of Money _Vandana  -   - Copy.pdf","baseUrl":"https:\/\/d2bps9p1kiy4ka.cloudfront.net\/","key":"5eb393ee95fab7468a79d189\/ce1ece8a-6331-465e-885b-33311d654ad0.pdf"}],"batchSubjectId":"63b594845998c500187494f5","solutionVideoType":"none"}],"dRoomId":"63eb5ffb128d7be1d2b939fa","isBatchDoubtEnabled":true}],"DppVideos":[{"_id":"6401a1e369973200180256eb","restrictedSchedule":false,"restrictedTime":0,"urlType":"penpencilvdo","tags":[{"_id":"63f99456d9d5db0018b298a1","name":"Time Value Of Money"}],"isFree":false,"isChatEnabled":false,"isDoubtEnabled":false,"isCommentDisabled":false,"isPathshala":false,"isDPPVideos":true,"status":"PENDING","topic":"Time Value Of Money Solution to DPP 05","date":"2023-03-03T18:29:59.000Z","startTime":"2023-03-03T08:30:00.000Z","endTime":"2023-03-03T08:30:00.000Z","url":"https:\/\/d1d34p8vz63oiq.cloudfront.net\/1ef3f3db-e2fe-4952-bffe-dd4a033bdb04\/master.mpd","timeline":[],"videoDetails":{"_id":"640183ff2f8f890018c6d191","id":"640183ff2f8f890018c6d191","name":"Time Value Of Money DPP 05","image":"https:\/\/d2bps9p1kiy4ka.cloudfront.net\/5eb393ee95fab7468a79d189\/39bf1aa8-13a2-4134-9e4f-7f623b3eb3ab.png","videoUrl":"https:\/\/d1d34p8vz63oiq.cloudfront.net\/1ef3f3db-e2fe-4952-bffe-dd4a033bdb04\/master.mpd","duration":"01:08:46","status":"Ready","types":["DASH","HLS"],"createdAt":"2023-03-03T05:22:07.352Z"},"dRoomId":"63eb5ffb128d7be1d2b939fa","isBatchDoubtEnabled":true},{"_id":"640039a26dbeca00186d5545","restrictedSchedule":false,"restrictedTime":0,"urlType":"penpencilvdo","tags":[{"_id":"63f99456d9d5db0018b298a1","name":"Time Value Of Money"}],"isFree":false,"isChatEnabled":false,"isDoubtEnabled":false,"isCommentDisabled":false,"isPathshala":false,"isDPPVideos":true,"status":"PENDING","topic":"Time Value Of Money Solution to DPP 04","date":"2023-03-02T18:29:59.000Z","startTime":"2023-03-02T08:30:00.000Z","endTime":"2023-03-02T08:30:00.000Z","url":"https:\/\/d1d34p8vz63oiq.cloudfront.net\/dcacdb7e-1b76-4521-9dcf-b11b05f8409f\/master.mpd","timeline":[],"videoDetails":{"_id":"64002e3bf7feeb0018ab7f2b","id":"64002e3bf7feeb0018ab7f2b","name":"Time Value Of Money DPP 04","image":"https:\/\/d2bps9p1kiy4ka.cloudfront.net\/5eb393ee95fab7468a79d189\/4bd7f279-c912-4877-9f33-7752413a5214.png","videoUrl":"https:\/\/d1d34p8vz63oiq.cloudfront.net\/dcacdb7e-1b76-4521-9dcf-b11b05f8409f\/master.mpd","duration":"01:36:11","status":"Ready","types":["DASH","HLS"],"createdAt":"2023-03-02T05:03:55.098Z"},"dRoomId":"63eb5ffb128d7be1d2b939fa","isBatchDoubtEnabled":true},{"_id":"63fee33f972ff8003acdc984","restrictedSchedule":false,"restrictedTime":0,"urlType":"penpencilvdo","tags":[{"_id":"63f99456d9d5db0018b298a1","name":"Time Value Of Money"}],"isFree":false,"isChatEnabled":false,"isDoubtEnabled":false,"isCommentDisabled":false,"isPathshala":false,"isDPPVideos":true,"status":"PENDING","topic":"Time Value Of Money Solution to DPP 03","date":"2023-03-01T18:29:59.000Z","startTime":"2023-03-01T08:30:00.000Z","endTime":"2023-03-01T08:30:00.000Z","url":"https:\/\/d1d34p8vz63oiq.cloudfront.net\/17e4da09-3ced-4473-9aab-19ab74a24930\/master.mpd","timeline":[],"videoDetails":{"_id":"63fedc5db821e400181f39b7","id":"63fedc5db821e400181f39b7","name":"Time Value Of Money  DPP 03","image":"https:\/\/d2bps9p1kiy4ka.cloudfront.net\/5eb393ee95fab7468a79d189\/c2c357cc-66e0-4d49-b881-5b73ddd3058f.png","videoUrl":"https:\/\/d1d34p8vz63oiq.cloudfront.net\/17e4da09-3ced-4473-9aab-19ab74a24930\/master.mpd","duration":"01:38:47","status":"Ready","types":["DASH","HLS"],"createdAt":"2023-03-01T05:02:21.240Z"},"dRoomId":"63eb5ffb128d7be1d2b939fa","isBatchDoubtEnabled":true},{"_id":"63fda2c617ae8900184e2939","restrictedSchedule":false,"restrictedTime":0,"urlType":"penpencilvdo","tags":[{"_id":"63f99456d9d5db0018b298a1","name":"Time Value Of Money"}],"isFree":false,"isChatEnabled":false,"isDoubtEnabled":false,"isCommentDisabled":false,"isPathshala":false,"isDPPVideos":true,"status":"PENDING","topic":"Time Value Of Money Solution to DPP 02","date":"2023-02-28T18:29:59.000Z","startTime":"2023-02-28T08:30:00.000Z","endTime":"2023-02-28T08:30:00.000Z","url":"https:\/\/d1d34p8vz63oiq.cloudfront.net\/5e5acf63-979c-4eed-a237-15f27a242cf7\/master.mpd","timeline":[],"videoDetails":{"_id":"63fd9543a5ba7400180fae8a","id":"63fd9543a5ba7400180fae8a","name":"Time Value Of Money DPP 02","image":"https:\/\/d2bps9p1kiy4ka.cloudfront.net\/5eb393ee95fab7468a79d189\/a36d3180-eee6-41b8-a0bc-34251b21a844.png","videoUrl":"https:\/\/d1d34p8vz63oiq.cloudfront.net\/5e5acf63-979c-4eed-a237-15f27a242cf7\/master.mpd","duration":"01:30:23","status":"Ready","types":["DASH","HLS"],"createdAt":"2023-02-28T05:46:43.978Z"},"dRoomId":"63eb5ffb128d7be1d2b939fa","isBatchDoubtEnabled":true},{"_id":"63fc56dd5afeaf0018c9a438","restrictedSchedule":false,"restrictedTime":0,"urlType":"penpencilvdo","tags":[{"_id":"63f99456d9d5db0018b298a1","name":"Time Value Of Money"}],"isFree":false,"isChatEnabled":false,"isDoubtEnabled":false,"isCommentDisabled":false,"isPathshala":false,"isDPPVideos":true,"status":"PENDING","topic":"Time Value Of Money Solution to DPP 01","date":"2023-02-27T18:29:59.000Z","startTime":"2023-02-27T08:30:00.000Z","endTime":"2023-02-27T08:30:00.000Z","url":"https:\/\/d1d34p8vz63oiq.cloudfront.net\/30513124-9bf7-48aa-81fc-a9674da87a4a\/master.mpd","timeline":[],"videoDetails":{"_id":"63fc3344c840f200660a3557","id":"63fc3344c840f200660a3557","name":"Time Value Of Money DPP 01","image":"https:\/\/d2bps9p1kiy4ka.cloudfront.net\/5eb393ee95fab7468a79d189\/1c68ce0c-b4d8-468b-aac2-d879b308c003.png","videoUrl":"https:\/\/d1d34p8vz63oiq.cloudfront.net\/30513124-9bf7-48aa-81fc-a9674da87a4a\/master.mpd","duration":"00:59:02","status":"Ready","types":["DASH","HLS"],"createdAt":"2023-02-27T04:36:20.915Z"},"dRoomId":"63eb5ffb128d7be1d2b939fa","isBatchDoubtEnabled":true}],"exercises":[]}