{"videos":[{"_id":"633f2b70a08cfd0011dcfa83","restrictedSchedule":false,"restrictedTime":0,"urlType":"penpencilvdo","isFree":false,"isChatEnabled":false,"isDoubtEnabled":true,"isCommentDisabled":false,"isPathshala":false,"isDPPVideos":false,"status":"COMPLETED","date":"2022-10-07T18:29:59.000Z","startTime":"2022-10-07T08:30:59.000Z","endTime":"2022-10-07T08:30:59.000Z","timeline":[],"topic":"Matrices -01 : Types of Matrix, Classification of Square Matrix, Algebra of Matrices, Trace and Determinant Value","conversationId":"633f2e579d5f8900110be4cb","url":"https:\/\/d1d34p8vz63oiq.cloudfront.net\/afb09b72-a01e-41dc-8b66-fbd3f8a6230d\/master.mpd","videoDetails":{"id":"634017a957ce7f00187f2d4b","name":"Matrices -01 : Types of Matrix, Classification of Square Matrix, Algebra of Matrices, Trace and Determinant Value","image":"https:\/\/d2bps9p1kiy4ka.cloudfront.net\/5eb393ee95fab7468a79d189\/96f4ff81-f2c1-48a6-924e-0f30c43f45d6.png","videoUrl":"https:\/\/d1d34p8vz63oiq.cloudfront.net\/afb09b72-a01e-41dc-8b66-fbd3f8a6230d\/master.mpd","description":"","duration":"02:44:20","status":"Ready","types":["DASH","HLS"]},"dRoomId":"62e53234c6cee700112e96f6","isBatchDoubtEnabled":true}],"notes":[{"_id":"633f2b70a08cfd0011dcfa83","homeworkIds":[{"attachmentIds":[{"baseUrl":"https:\/\/d2bps9p1kiy4ka.cloudfront.net\/","_id":"6340103a9fe75e0018d5a700","name":"Matrices -01 (Class Notes).pdf","key":"5eb393ee95fab7468a79d189\/f3ebcf8c-87d2-42eb-9e43-9754b8b413d4.pdf"}],"actions":["Open","Download","Print"],"_id":"63400d6c4afda20018d913f6","batchSubjectId":"62ef5f6236dc900011b88ee4","topic":"Matrices -01  : Class Notes || (Prayas 2.0 2023 PW Star)","note":"Class Notes"}],"isFree":false,"isDPPNotes":false,"status":"COMPLETED","date":"2022-10-07T18:29:59.000Z","startTime":"2022-10-07T08:30:59.000Z","dRoomId":"62e53234c6cee700112e96f6","isBatchDoubtEnabled":true}],"DppNotes":[{"_id":"63400dbd3e647400110445f5","homeworkIds":[{"attachmentIds":[{"baseUrl":"https:\/\/d2bps9p1kiy4ka.cloudfront.net\/","_id":"63400d94f992150018c516af","name":"Matrices (DPP 01).pdf","key":"5eb393ee95fab7468a79d189\/f682da73-aa28-4668-84e2-462556ec8fc4.pdf"}],"actions":["Open","Download","Print"],"_id":"63400d95b0112100185e910c","batchSubjectId":"62ef5f6236dc900011b88ee4","topic":"Matrices : DPP 01 || (Prayas 2.0 2023 PW Star)","note":"DPP"}],"isFree":false,"isDPPNotes":true,"status":"PENDING","date":"2022-10-07T18:29:59.000Z","startTime":"2022-10-07T08:30:59.000Z","dRoomId":"62e53234c6cee700112e96f6","isBatchDoubtEnabled":true}],"DppVideos":[],"exercises":[{"_id":"63400dbd3e647400110445f5","isFree":false,"status":"PENDING","date":"2022-10-07T18:29:59.000Z","startTime":"2022-10-07T08:30:59.000Z","exerciseIds":[{"type":"Exercise","availableFor":[],"status":"Active","title":"Matrices : DPP 01 MCQ-Quiz","content":[{"_id":"63401fb7cc54ce0018fdd83f","exerciseId":"63401fb793bec40018960ebf","timeline":[]}],"slug":"matrices---dpp-01-mcq-quiz-383481"}],"dRoomId":"62e53234c6cee700112e96f6","isBatchDoubtEnabled":true}]}