{"videos":[],"notes":[{"_id":"632c1f7b31e39800187a2c47","homeworkIds":[{"attachmentIds":[{"baseUrl":"https:\/\/d2bps9p1kiy4ka.cloudfront.net\/","_id":"632c1fad1ec47800182dfce5","name":"motion 2d (1).pdf","key":"5eb393ee95fab7468a79d189\/15ad202c-6cf8-4537-a3fd-fdb4538a6c9a.pdf"}],"actions":["Open","Download","Print"],"_id":"632c1fed0303da0019b01ea3","batchSubjectId":"621c630c79f45400113aeda8","topic":"Motion in a Plane : Short Notes || (Arjuna NEET 2023)","note":"Classnotes"},{"attachmentIds":[{"baseUrl":"https:\/\/d2bps9p1kiy4ka.cloudfront.net\/","_id":"6327f5b8328767001169fdc4","name":"Short Practice Test 05 _ Test Syllabus (25_08_2022) .pdf","key":"5eb393ee95fab7468a79d189\/cc45607f-6bee-4eb3-84bc-486d80fc8bf0.pdf"}],"actions":["Open","Download","Print"],"_id":"6327f5bbc2e70400180711ab","batchSubjectId":"621c630c79f45400113aeda8","topic":"Short Practice Test 05 : Test Syllabus (25-09-2022) || Arjuna NEET 2023","note":"Test Syllabus"},{"attachmentIds":[{"baseUrl":"https:\/\/d2bps9p1kiy4ka.cloudfront.net\/","_id":"62a1fbbb5edbc60011f345ef","name":"Telegram Link.pdf","key":"5eb393ee95fab7468a79d189\/56a2769b-d0cf-40d1-817d-33f84970bb06.pdf"}],"actions":["Open","Download","Print"],"_id":"62a0dd43f23aa10018bb7a6e","batchSubjectId":"621c630c79f45400113aeda8","topic":"Arjuna NEET 2023 : Telegram Group Link","note":"Telegram Link"}],"isFree":false,"isDPPNotes":false,"status":"PENDING","date":"2022-09-22T18:29:59.000Z","startTime":"2022-09-22T07:30:59.000Z","dRoomId":"62a07612de43f000117d73cf","isBatchDoubtEnabled":true},{"_id":"630db22bbf62f800187ad7de","homeworkIds":[{"attachmentIds":[{"baseUrl":"https:\/\/d2bps9p1kiy4ka.cloudfront.net\/","_id":"630db1e5a6cb7f0019dad88f","name":"Motion in a Straight Line Short Notes.pdf","key":"5eb393ee95fab7468a79d189\/7cffb796-cbaa-4a0e-94e7-27d181e10423.pdf"}],"actions":["Open","Download","Print"],"_id":"630db1e68fe7f00018e63f0f","batchSubjectId":"621c630c79f45400113aeda8","topic":"Motion in a Straight Line: Short Notes (PDF Only) || Arjuna NEET 2023","note":"Short Notes"}],"isFree":false,"isDPPNotes":false,"status":"PENDING","date":"2022-08-30T18:29:59.000Z","startTime":"2022-08-30T13:00:59.000Z","dRoomId":"62a07612de43f000117d73cf","isBatchDoubtEnabled":true}],"DppNotes":[],"DppVideos":[],"exercises":[]}